drf_cli/__init__.py
drf_cli/__main__.py
drf_cli/commands/__init__.py
drf_cli/commands/init.py
skn_drf_cli-1.0.1.dist-info/LICENSE
skn_drf_cli-1.0.1.dist-info/METADATA
skn_drf_cli-1.0.1.dist-info/WHEEL
skn_drf_cli-1.0.1.dist-info/entry_points.txt
skn_drf_cli-1.0.1.dist-info/top_level.txt
skn_drf_cli-1.0.1.dist-info/RECORD
