Metadata-Version: 2.1
Name: skn-drf-cli
Version: 1.0.1
Summary: Django Rest Framework command-line tools
Home-page: https://github.com/shywn-mrk/drf-cli
Author: Shayan Karimi
Author-email: shayankarimi0078@gmail.com
License: UNKNOWN
Platform: UNKNOWN
Classifier: Programming Language :: Python :: 3
Classifier: License :: OSI Approved :: MIT License
Classifier: Operating System :: OS Independent
Requires-Python: >=3.6
Requires-Dist: click (<7.2,>=7.1)
